sedreh_geoserver/__init__.py
sedreh_geoserver/api.py
sedreh_geoserver-0.0.3.dist-info/LICENSE.txt
sedreh_geoserver-0.0.3.dist-info/METADATA
sedreh_geoserver-0.0.3.dist-info/WHEEL
sedreh_geoserver-0.0.3.dist-info/top_level.txt
sedreh_geoserver-0.0.3.dist-info/RECORD
