Metadata-Version: 2.1
Name: sedreh-geoserver
Version: 0.0.3
Summary: geoserver customize for sedreh satellite
Home-page: UNKNOWN
Author: Sedreh-Corporation
Author-email: sedrehgroup@gmail.com
License: UNKNOWN
Platform: UNKNOWN
License-File: LICENSE.txt
Requires-Dist: requests
